ninja_zip_streamer/__init__.py
ninja_zip_streamer/core.py
ninja_zip_streamer/py.typed
ninja_zip_streamer/utils.py
ninja_zip_streamer-0.0.6.dist-info/licenses/LICENSE
ninja_zip_streamer-0.0.6.dist-info/METADATA
ninja_zip_streamer-0.0.6.dist-info/WHEEL
ninja_zip_streamer-0.0.6.dist-info/top_level.txt
ninja_zip_streamer-0.0.6.dist-info/RECORD
