Metadata-Version: 2.4
Name: ninja-zip-streamer
Version: 0.0.6
Summary: Streams remote zip files without using filesystem cache.
Author-email: Rémi Cresson <remi.cresson@inrae.fr>
License: Apache-2.0
Classifier: Programming Language :: Python :: 3.9
Classifier: Programming Language :: Python :: 3.10
Classifier: Programming Language :: Python :: 3.11
Classifier: License :: OSI Approved :: Apache Software License
Requires-Python: >=3.9
License-File: LICENSE
Requires-Dist: setuptools>=61.2
Requires-Dist: stream-unzip
Requires-Dist: requests>=2.25.1
Requires-Dist: packaging
Dynamic: license-file
